CustomizableSocketServer/BaseClient.py
CustomizableSocketServer/BaseServer.py
CustomizableSocketServer/SocketOperations.py
CustomizableSocketServer/__init__.py
CustomizableSocketServer/exceptions.py
CustomizableSocketServer/schemas.py
CustomizableSocketServer-2.3.0.dist-info/LICENSE
CustomizableSocketServer-2.3.0.dist-info/METADATA
CustomizableSocketServer-2.3.0.dist-info/WHEEL
CustomizableSocketServer-2.3.0.dist-info/entry_points.txt
CustomizableSocketServer-2.3.0.dist-info/top_level.txt
CustomizableSocketServer-2.3.0.dist-info/RECORD
